arithmetics_sdd/__init__.py
arithmetics_sdd/main.py
arithmetics_sdd/Text/afrikaans.txt
arithmetics_sdd/Text/albanian.txt
arithmetics_sdd/Text/amharic.txt
arithmetics_sdd/Text/arabic.txt
arithmetics_sdd/Text/armenian.txt
arithmetics_sdd/Text/azerbaijani.txt
arithmetics_sdd/Text/basque.txt
arithmetics_sdd/Text/belarusian.txt
arithmetics_sdd/Text/bengali.txt
arithmetics_sdd/Text/bosnian.txt
arithmetics_sdd/Text/bulgarian.txt
arithmetics_sdd/Text/catalan.txt
arithmetics_sdd/Text/cebuano.txt
arithmetics_sdd/Text/chichewa.txt
arithmetics_sdd/Text/chinese (simplified).txt
arithmetics_sdd/Text/chinese (traditional).txt
arithmetics_sdd/Text/corsican.txt
arithmetics_sdd/Text/croatian.txt
arithmetics_sdd/Text/czech.txt
arithmetics_sdd/Text/danish.txt
arithmetics_sdd/Text/dutch.txt
arithmetics_sdd/Text/english.txt
arithmetics_sdd/Text/esperanto.txt
arithmetics_sdd/Text/estonian.txt
arithmetics_sdd/Text/filipino.txt
arithmetics_sdd/Text/finnish.txt
arithmetics_sdd/Text/french.txt
arithmetics_sdd/Text/frisian.txt
arithmetics_sdd/Text/galician.txt
arithmetics_sdd/Text/georgian.txt
arithmetics_sdd/Text/german.txt
arithmetics_sdd/Text/greek.txt
arithmetics_sdd/Text/gujarati.txt
arithmetics_sdd/Text/haitian creole.txt
arithmetics_sdd/Text/hausa.txt
arithmetics_sdd/Text/hawaiian.txt
arithmetics_sdd/Text/hebrew.txt
arithmetics_sdd/Text/hindi.txt
arithmetics_sdd/Text/hmong.txt
arithmetics_sdd/Text/hungarian.txt
arithmetics_sdd/Text/icelandic.txt
arithmetics_sdd/Text/igbo.txt
arithmetics_sdd/Text/indonesian.txt
arithmetics_sdd/Text/irish.txt
arithmetics_sdd/Text/italian.txt
arithmetics_sdd/Text/japanese.txt
arithmetics_sdd/Text/javanese.txt
arithmetics_sdd/Text/kannada.txt
arithmetics_sdd/Text/kazakh.txt
arithmetics_sdd/Text/khmer.txt
arithmetics_sdd/Text/korean.txt
arithmetics_sdd/Text/kurdish (kurmanji).txt
arithmetics_sdd/Text/kyrgyz.txt
arithmetics_sdd/Text/lao.txt
arithmetics_sdd/Text/latin.txt
arithmetics_sdd/Text/latvian.txt
arithmetics_sdd/Text/lithuanian.txt
arithmetics_sdd-1.1.dist-info/LICENSE
arithmetics_sdd-1.1.dist-info/METADATA
arithmetics_sdd-1.1.dist-info/WHEEL
arithmetics_sdd-1.1.dist-info/entry_points.txt
arithmetics_sdd-1.1.dist-info/top_level.txt
arithmetics_sdd-1.1.dist-info/RECORD
