Metadata-Version: 2.1
Name: arithmetics_sdd
Version: 1.1
Summary: This program is designed to develop basic arithmetic skills
Home-page: https://github.com/Shayem1/Understanding-Arithmetics-Interactive-Experience
Author: Shayem Quazi
License: MIT
Classifier: Topic :: Multimedia
Classifier: Development Status :: 5 - Production/Stable
Classifier: Intended Audience :: End Users/Desktop
Classifier: Intended Audience :: Developers
Classifier: Intended Audience :: Education
Classifier: License :: OSI Approved :: MIT License
Classifier: Programming Language :: Python
Classifier: Programming Language :: Python :: 3
Classifier: Topic :: Education
Classifier: Topic :: Games/Entertainment
License-File: LICENSE
Requires-Dist: customtkinter
Requires-Dist: pyttsx3
Requires-Dist: Pillow
